LAB/LAB 9/Ejercicio 3/ejercicio3.v
//Ejercicio 3

module FlipD1(input wire CLK, input wire D, input wire reset, input wire enable, output Q);
reg Q;
	always @(posedge CLK or	posedge reset or posedge enable)
		if (reset)begin
		Q <= 0;
	end else if(enable) begin
		Q <= D;
	end
endmodule

//modulo FlipFlop JK
module FlipJK(input wire CLK, reset, enable, J, K, output wire Q);
	FlipD1 O5(CLK, ~K&Q | J&~Q, reset, enable, Q);
endmodule

LAB/LAB 9/Ejercicio 3/ejercicio3_tb.v
module Ejercicio_3();

  reg Clk, reset, enable, K, J; 
  wire QJK; 

//Variables para módulo
	FlipJK U4(Clk, reset, enable, J, K, QJK);


initial begin
	Clk=0;
	forever #5 Clk = ~Clk;
end


//Prueba para FLipJK
  initial begin
	#3
    $display("\n");
	$display("Ejercicio 2");
    $display("Clk J K |  Q");
    $display("-----------------");
    $monitor("%b   %b %b | %b", Clk, J, K, QJK);
       reset = 1; enable = 0; J = 0; K = 0;
    #1 reset = 0; enable = 1;
	#10 J = 1;
	#15 J = 0; K = 1;
	#15 J = 1;

  end

	initial
    #70 $finish;
  initial begin
    $dumpfile("ejercicio3_tb.vcd");
    $dumpvars(0, Ejercicio_3);
  end
endmodule

LAB/LAB 9/Ejercicio 3/ejercicio3_tb.vcd
$date
	Fri Oct 30 16:33:54 2020
$end
$version
	Icarus Verilog
$end
$timescale
	1ps
$end
$scope module Ejercicio_3 $end
$var wire 1 ! QJK $end
$var reg 1 " Clk $end
$var reg 1 # J $end
$var reg 1 $ K $end
$var reg 1 % enable $end
$var reg 1 & reset $end
$scope module U4 $end
$var wire 1 " CLK $end
$var wire 1 # J $end
$var wire 1 $ K $end
$var wire 1 % enable $end
$var wire 1 & reset $end
$var wire 1 ! Q $end
$scope module O5 $end
$var wire 1 " CLK $end
$var wire 1 ' D $end
$var wire 1 % enable $end
$var wire 1 & reset $end
$var reg 1 ! Q $end
$upscope $end
$upscope $end
$upscope $end
$enddefinitions $end
#0
$dumpvars
x'
x&
x%
x$
x#
0"
x!
$end
#3
0'
0!
0$
0#
0%
1&
#4
1%
0&
#5
1"
#10
0"
#14
1'
1#
#15
1!
1"
#20
0"
#25
1"
#29
0'
1$
0#
#30
0"
#35
0!
1"
#40
0"
#44
1'
1#
#45
0'
1!
1"
#50
0"
#55
1'
0!
1"
#60
0"
#65
0'
1!
1"
