LAB/LAB 10/Ejercicio 2/ejercicio2Lab10.v
//Ejercicio 1

//Bus Driver
module BufTri(input wire enable, input wire [3:0]IN, output wire [3:0]OUT);
	assign OUT = enable ? IN : 4'bz;
endmodule


//ALU
module ALU (input wire [3:0]A, input wire [3:0]B, input wire [2:0]sel, output reg [3:0]Y, output reg zero, output reg carry); 
reg [4:0]X;

	always @ (A or B or sel) 
		case (sel) 
			0 : begin
				Y = A;
				zero = ~Y[0]&~Y[1]&~Y[2]&~Y[3];
				end
			1 : begin
				X = A - B; 
				Y[0] = X[0];
				Y[1] = X[1];
				Y[2] = X[2];
				Y[3] = X[3];
				carry = X[4];
				zero = ~Y[0]&~Y[1]&~Y[2]&~Y[3];
				end 
			2 : begin
				Y = B;
				zero = ~Y[0]&~Y[1]&~Y[2]&~Y[3];
				end
			3 : begin
				X = A + B; 
				Y[0] = X[0];
				Y[1] = X[1];
				Y[2] = X[2];
				Y[3] = X[3];
				carry = X[4];
				zero = ~Y[0]&~Y[1]&~Y[2]&~Y[3];
				end
			4 : begin
				Y = ~(A&B);
				zero = ~Y[0]&~Y[1]&~Y[2]&~Y[3];
				end
			default : $display("Error in SEL"); 
		endcase 
endmodule


//Accumulador
module ACC(input wire CLK, input wire [3:0]D, input wire reset, input wire enable, output [3:0]Q);
reg Q;
	always @(posedge CLK or	posedge reset or posedge enable)
		if (reset)begin
		Q <= 0;
	end else if(enable) begin
		Q <= D;
	end
endmodule


//modulo final
module Eje2(input wire clk, reset, enable1, enable2, enable3, input wire [3:0]IN, input wire [2:0]sel, output wire [3:0]Y, output wire zero, carry);
	wire [3:0]YBuf1;
	wire [3:0]YACC;
	wire [3:0]YALU;
	BufTri O1(enable1, IN, YBuf1);
	ACC O3(clk, YALU, reset, enable3, YACC);
	ALU O2(YACC, YBuf1, sel, YALU, zero, carry);
	BufTri O4(enable2, YALU, Y);
endmodule

LAB/LAB 10/Ejercicio 2/ejercicio2Lab10_tb.v
module Ejercicio_2LAB10();

  reg Clk, enable1, enable2, enable3, reset; reg [3:0]IN; reg [2:0]sel;
  wire [3:0]Y; wire zero, carry;

//Variables para módulo
	Eje2 U1(Clk, reset, enable1, enable2, enable3, IN, sel, Y, zero, carry);


//Prueba para FLipFlop de 1 bit
initial begin
	Clk=0;
	forever #5 Clk = ~Clk;
end
  initial begin
	#3
    $display("\n");
	$display("         EJERCICIO 2\n");
    $display("CLK R E1 E2 E3  IN   Sel | Y   zero carry");
    $display("-------------------------------------------");
    $monitor("%b   %b %b  %b  %b  %b  %b | %b  %b    %b", Clk, reset, enable1, enable2, enable3, IN, sel, Y, zero, carry);
	//es escogieron números aleatorios para A
       reset = 1; enable1 = 0; enable2 = 0; enable3 = 0; IN = 0; sel = 0;
	   #10 reset = 0; enable1 = 1; enable2 = 1; enable3 = 1;
	   #10 IN = 1;
	   #10 IN = 2;
	   #10 IN = 3;
	   #10 IN = 10;
	   #10 sel = 2;
	   #10 IN = 10;
	   #10 sel = 1; IN = 5;
	   #10 sel = 3;
	   #20 sel = 4;   
  end



	initial
    #130 $finish;
  initial begin
    $dumpfile("ejercicio2Lab10_tb.vcd");
    $dumpvars(0, Ejercicio_2LAB10);
  end
endmodule

LAB/LAB 10/Ejercicio 2/ejercicio2Lab10x_tb.vcd
$date
	Thu Nov 05 17:53:07 2020
$end
$version
	Icarus Verilog
$end
$timescale
	1ps
$end
$scope module Ejercicio_2LAB10 $end
$var wire 1 ! zero $end
$var wire 1 " carry $end
$var wire 4 # Y [3:0] $end
$var reg 1 $ Clk $end
$var reg 4 % IN [3:0] $end
$var reg 1 & enable1 $end
$var reg 1 ' enable2 $end
$var reg 1 ( enable3 $end
$var reg 1 ) reset $end
$var reg 3 * sel [2:0] $end
$scope module U1 $end
$var wire 4 + IN [3:0] $end
$var wire 1 $ clk $end
$var wire 1 & enable1 $end
$var wire 1 ' enable2 $end
$var wire 1 ( enable3 $end
$var wire 1 ) reset $end
$var wire 3 , sel [2:0] $end
$var wire 1 ! zero $end
$var wire 1 " carry $end
$var wire 4 - YBuf1 [3:0] $end
$var wire 4 . YALU [3:0] $end
$var wire 4 / YACC [3:0] $end
$var wire 4 0 Y [3:0] $end
$scope module O1 $end
$var wire 4 1 IN [3:0] $end
$var wire 1 & enable $end
$var wire 4 2 OUT [3:0] $end
$upscope $end
$scope module O2 $end
$var wire 4 3 B [3:0] $end
$var wire 3 4 sel [2:0] $end
$var wire 4 5 A [3:0] $end
$var reg 5 6 X [4:0] $end
$var reg 4 7 Y [3:0] $end
$var reg 1 " carry $end
$var reg 1 ! zero $end
$upscope $end
$scope module O3 $end
$var wire 1 $ CLK $end
$var wire 4 8 D [3:0] $end
$var wire 1 ( enable $end
$var wire 1 ) reset $end
$var reg 4 9 Q [3:0] $end
$upscope $end
$scope module O4 $end
$var wire 4 : IN [3:0] $end
$var wire 1 ' enable $end
$var wire 4 ; OUT [3:0] $end
$upscope $end
$upscope $end
$upscope $end
$enddefinitions $end
#0
$dumpvars
bx ;
bx :
bx 9
bx 8
bx 7
bx 6
bx 5
bx 4
bx 3
bx 2
bx 1
bx 0
bx /
bx .
bx -
bx ,
bx +
bx *
x)
x(
x'
x&
bx %
0$
bx #
x"
x!
$end
#3
1!
b0 .
b0 7
b0 8
b0 :
b0 /
b0 5
b0 9
bz #
bz 0
bz ;
bz -
bz 2
bz 3
b0 *
b0 ,
b0 4
b0 %
b0 +
b0 1
0(
0'
0&
1)
#5
1$
#10
0$
#13
b0 #
b0 0
b0 ;
b0 -
b0 2
b0 3
1(
1'
1&
0)
#15
1$
#20
0$
#23
b1 -
b1 2
b1 3
b1 %
b1 +
b1 1
#25
1$
#30
0$
#33
b10 -
b10 2
b10 3
b10 %
b10 +
b10 1
#35
1$
#40
0$
#43
b11 -
b11 2
b11 3
b11 %
b11 +
b11 1
#45
1$
#50
0$
#53
b1010 -
b1010 2
b1010 3
b1010 %
b1010 +
b1010 1
#55
1$
#60
0$
#63
b1010 #
b1010 0
b1010 ;
0!
b1010 .
b1010 7
b1010 8
b1010 :
b10 *
b10 ,
b10 4
#65
b1010 /
b1010 5
b1010 9
1$
#70
0$
#75
1$
#80
0$
#83
b101 #
b101 0
b101 ;
b101 -
b101 2
b101 3
0!
0"
b101 .
b101 7
b101 8
b101 :
b101 6
b101 %
b101 +
b101 1
b1 *
b1 ,
b1 4
#85
b0 #
b0 0
b0 ;
1!
b0 .
b0 7
b0 8
b0 :
b0 6
b101 /
b101 5
b101 9
1$
#90
0$
#93
b1010 #
b1010 0
b1010 ;
0!
b1010 .
b1010 7
b1010 8
b1010 :
b1010 6
b11 *
b11 ,
b11 4
#95
b1111 #
b1111 0
b1111 ;
b1111 .
b1111 7
b1111 8
b1111 :
b1111 6
b1010 /
b1010 5
b1010 9
1$
#100
0$
#105
b100 #
b100 0
b100 ;
1"
b100 .
b100 7
b100 8
b100 :
b10100 6
b1111 /
b1111 5
b1111 9
1$
#110
0$
#113
b1010 #
b1010 0
b1010 ;
b1010 .
b1010 7
b1010 8
b1010 :
b100 *
b100 ,
b100 4
#115
b1111 #
b1111 0
b1111 ;
b1111 .
b1111 7
b1111 8
b1111 :
b1010 /
b1010 5
b1010 9
1$
#120
0$
#125
b1010 #
b1010 0
b1010 ;
b1010 .
b1010 7
b1010 8
b1010 :
b1111 /
b1111 5
b1111 9
1$
