LAB/LAB 9/Ejercicio 1/ejercicio1.v
//Ejercicio 1

//Modulo FlipFlopD de 1 bit
module FlipD1(input wire CLK, input wire D, input wire reset, input wire enable, output Q);
reg Q;
	always @(posedge CLK or	posedge reset or posedge enable)
		if (reset)begin
		Q <= 0;
	end else if(enable) begin
		Q <= D;
	end
endmodule


//Modulo FlipFlopD de 2 bit
module FlipD2 (input wire CLK, input wire [1:0]D, input wire reset, input wire enable, output wire [1:0]Q);
	FlipD1 O0(CLK, D[0], reset, enable, Q[0]);
	FlipD1 O1(CLK, D[1], reset, enable, Q[1]);
endmodule


//Modulo FlipFlopD de 4 bitsx
module FlipD4 (input wire CLK, input wire [3:0]D, input wire reset, input wire enable, output wire [3:0]Q);
	FlipD2 O3(CLK, D[1:0], reset, enable, Q[1:0]);
	FlipD2 O4(CLK, D[3:2], reset, enable, Q[3:2]);
endmodule

LAB/LAB 9/Ejercicio 1/ejercicio1_tb.v
module Ejercicio_1();

  reg Clk, reset, D1, enable; reg [1:0]D2; reg [3:0]D4; 
  wire Q1; wire [1:0]Q2; wire [3:0]Q4;

//Variables para módulo
	FlipD1 U1(Clk, D1, reset, enable, Q1);
	FlipD2 U2(Clk, D2, reset, enable, Q2);
	FlipD4 U3(Clk, D4, reset, enable, Q4);


//Prueba para FLipFlop de 1 bit
initial begin
	Clk=0;
	forever #5 Clk = ~Clk;
end
  initial begin
	#3
    $display("\n");
	$display("Ejercicio 1, FlipFlop D 1 bit");
    $display("Clk E D | Q");
    $display("------------");
    $monitor("%b   %b %b | %b", Clk, enable, D1, Q1);
	//es escogieron números aleatorios para A
       reset = 1; D1 = 1; enable = 0;
    #1 reset = 0;
	#10 D1 = 1;
	#10 enable = 1;
	#15 D1 = 0;
  end


//Prueba para FLipFlop de 2 bit
  initial begin
	#60
    $display("\n");
	$display("Ejercicio 1, FlipFlop D 2 bits");
    $display("Clk E  D | Q");
    $display("-------------");
    $monitor("%b   %b %b |%b", Clk, enable, D2, Q2);
	//es escogieron números aleatorios para A
       reset = 1; D2 = 1;
    #1 reset = 0;
	#5 enable = 1;
	#10 D2 = 2;
	#10 D2 = 3;
  end
 
 
//Prueba para FLipFlop de 4 bit
  initial begin
	#105
    $display("\n");
	$display("Ejercicio 1, FlipFlop D 4 bits");
    $display("Clk E  D   |  Q");
    $display("-----------------");
    $monitor("%b   %b %b | %b", Clk, enable, D4, Q4);
	//es escogieron números aleatorios para A
       reset = 1; D4 = 1;
    #1 reset = 0;
	#5 enable = 1;
	#10 D4 = 2;
	#10 D4 = 3;
	#10 D4 = 10;
  end


	initial
    #150 $finish;
  initial begin
    $dumpfile("ejercicio1_tb.vcd");
    $dumpvars(0, Ejercicio_1);
  end
endmodule

LAB/LAB 9/Ejercicio 1/ejercicio1_tb.vcd
$date
	Fri Oct 30 16:15:03 2020
$end
$version
	Icarus Verilog
$end
$timescale
	1ps
$end
$scope module Ejercicio_1 $end
$var wire 4 ! Q4 [3:0] $end
$var wire 2 " Q2 [1:0] $end
$var wire 1 # Q1 $end
$var reg 1 $ Clk $end
$var reg 1 % D1 $end
$var reg 2 & D2 [1:0] $end
$var reg 4 ' D4 [3:0] $end
$var reg 1 ( enable $end
$var reg 1 ) reset $end
$scope module U1 $end
$var wire 1 $ CLK $end
$var wire 1 % D $end
$var wire 1 ( enable $end
$var wire 1 ) reset $end
$var reg 1 # Q $end
$upscope $end
$scope module U2 $end
$var wire 1 $ CLK $end
$var wire 2 * D [1:0] $end
$var wire 1 ( enable $end
$var wire 1 ) reset $end
$var wire 2 + Q [1:0] $end
$scope module O0 $end
$var wire 1 $ CLK $end
$var wire 1 , D $end
$var wire 1 ( enable $end
$var wire 1 ) reset $end
$var reg 1 - Q $end
$upscope $end
$scope module O1 $end
$var wire 1 $ CLK $end
$var wire 1 . D $end
$var wire 1 ( enable $end
$var wire 1 ) reset $end
$var reg 1 / Q $end
$upscope $end
$upscope $end
$scope module U3 $end
$var wire 1 $ CLK $end
$var wire 4 0 D [3:0] $end
$var wire 1 ( enable $end
$var wire 1 ) reset $end
$var wire 4 1 Q [3:0] $end
$scope module O3 $end
$var wire 1 $ CLK $end
$var wire 2 2 D [1:0] $end
$var wire 1 ( enable $end
$var wire 1 ) reset $end
$var wire 2 3 Q [1:0] $end
$scope module O0 $end
$var wire 1 $ CLK $end
$var wire 1 4 D $end
$var wire 1 ( enable $end
$var wire 1 ) reset $end
$var reg 1 5 Q $end
$upscope $end
$scope module O1 $end
$var wire 1 $ CLK $end
$var wire 1 6 D $end
$var wire 1 ( enable $end
$var wire 1 ) reset $end
$var reg 1 7 Q $end
$upscope $end
$upscope $end
$scope module O4 $end
$var wire 1 $ CLK $end
$var wire 2 8 D [1:0] $end
$var wire 1 ( enable $end
$var wire 1 ) reset $end
$var wire 2 9 Q [1:0] $end
$scope module O0 $end
$var wire 1 $ CLK $end
$var wire 1 : D $end
$var wire 1 ( enable $end
$var wire 1 ) reset $end
$var reg 1 ; Q $end
$upscope $end
$scope module O1 $end
$var wire 1 $ CLK $end
$var wire 1 < D $end
$var wire 1 ( enable $end
$var wire 1 ) reset $end
$var reg 1 = Q $end
$upscope $end
$upscope $end
$upscope $end
$upscope $end
$enddefinitions $end
#0
$dumpvars
x=
x<
x;
x:
bx 9
bx 8
x7
x6
x5
x4
bx 3
bx 2
bx 1
bx 0
x/
x.
x-
x,
bx +
bx *
x)
x(
bx '
bx &
x%
0$
x#
bx "
bx !
$end
#3
0#
0-
b0 "
b0 +
0/
05
b0 3
07
0;
b0 !
b0 1
b0 9
0=
0(
1%
1)
#4
0)
#5
1$
#10
0$
#15
1$
#20
0$
#24
x=
bx 9
x;
x7
bx !
bx 1
bx 3
x5
x/
bx "
bx +
x-
1#
1(
#25
1$
#30
0$
#35
1$
#39
0%
#40
0$
#45
0#
1$
#50
0$
#55
1$
#60
0-
b0 "
b0 +
0/
05
b0 3
07
0;
b0 !
b0 1
b0 9
0=
1,
0.
0$
b1 &
b1 *
1)
#61
0)
#65
x=
bx 9
x;
x7
bx !
bx 1
bx 3
x5
b1 "
b1 +
1-
1$
#70
0$
#75
1$
#76
0,
1.
b10 &
b10 *
#80
0$
#85
1/
b10 "
b10 +
0-
1$
#86
1,
b11 &
b11 *
#90
0$
#95
b11 "
b11 +
1-
1$
#100
0$
#105
0=
b0 9
0;
07
b0 !
b0 1
b0 3
05
0/
b0 "
b0 +
0-
14
06
0:
0<
b1 2
b0 8
1$
b1 '
b1 0
1)
#106
0)
#110
0$
#115
1-
b11 "
b11 +
1/
b1 !
b1 1
b1 3
15
1$
#120
0$
#121
04
16
b10 2
b10 '
b10 0
#125
17
b10 !
b10 1
b10 3
05
1$
#130
0$
#131
14
b11 2
b11 '
b11 0
#135
b11 !
b11 1
b11 3
15
1$
#140
0$
#141
04
1<
b10 2
b10 8
b1010 '
b1010 0
#145
b10 9
1=
b1010 !
b1010 1
b10 3
05
1$
