LAB/LAB 4/ejercicio 4/codigoEjercicio4.v
 

// Ecuación a implementar: Y = AB' + AC' + AD' + B'C'D'
module Ejer2Tabla1(input wire A, B, C, D, output wire Y);
//Outputs de gates
  wire NB, NC, ND, A1, A2, A3, A4;
//programación gates
  not (NB, B);
  not (NC, C);
  not (ND, D);
  and (A1, A, NB);
  and (A2, A, NC);
  and (A3, A, ND);
  and (A4, NB, NC, ND);
  or  (Y, A1, A2, A3, A4);

endmodule


// Ecuación a implementar: Y = C + B'
module Ejer2Tabla2(input wire A, B, C, output wire Y);
//output de gates
  wire NB;
//programación de gates
  not (NB, B);
  or  (Y, NB, C);

endmodule


// Ecuación a implementar: Y = B + C'D + AD
module Ejer2Tabla3(input wire A, B, C, D, output wire Y);
//output de gates
  wire NC, A1, A2;
//programación de gates
  not (NC, C);
  and (A1, NC, D);
  and (A2, A, D);
  or  (Y, A1, A2, B);

endmodule


// Ecuación a implementar: Y = A'C' + B
module Ejer2Tabla4(input wire A, B, C, output wire Y);
//output de gates
  wire NA, NC, A1;
//programación de gates
  not (NA, A);
  not (NC, C);
  and (A1, NA, NC);
  or  (Y, A1, B);

endmodule


//Cominezo progra utilizando operadores lógicos

//Ecuación a implementar: AC + AB' +A'C'
module Ejer1Tabla1(input wire A, B, C, output wire Y);

  assign Y = (A&C)|(A&~B)|(~A&~C);

endmodule


//Ecuación a implementar: B'
module Ejer1Tabla2(input wire A, B, C, output wire Y);

  assign Y = ~B;

endmodule


//Ecuación a implementar: A'B'C'D' + ABC'D' + A'BC'D + AB'C'D + A'B'CD + ABCD + A'BCD' + AB'CD'
module Ejer1Tabla3(input wire A, B, C, D, output wire Y);

  assign Y = (~A&~B&~C&~D)|(A&B&~C&~D)|(~A&B&~C&D)|(A&~B&~C&D)|(~A&~B&C&D)|(A&B&C&D)|(~A&B&C&~D)|(A&~B&C&~D);

endmodule


//Ecuación a implementar: AB + AC+ AD'
module Ejer1Tabla4(input wire A, B, C, D, output wire Y);

  assign Y = (A&B)|(A&C)|(A&~D);

endmodule

LAB/LAB 4/ejercicio 4/codigoEjercicio4_tb.v
module testbench();

//   | Var ejer1T1  |  Var ejer1T2 |    Var ejer1T3    |    Var ejer1T4   |    Var ejer2T1    |  Var ejer2T2  |    Var ejer2T3   | Var ejer2T4 | 
  reg A11, B11, C11, A12, B12, C12, A13, B13, C13, D13, A14, B14, C14, D14, A21, B21, C21, D21, A22, B22, C22, A23, B23, C23, D23, A24, B24, C24;
  wire YE1T1, YE1T2, YE1T3, YE1T4, YE2T1, YE2T2, YE2T3, YE2T4 ;

//Declaración Gate Level Modelling
  Ejer2Tabla1 G1(A21, B21, C21, D21, YE2T1);
  Ejer2Tabla2 G2(A22, B22, C22, YE2T2);
  Ejer2Tabla3 G3(A23, B23, C23, D23, YE2T3);
  Ejer2Tabla4 G4(A24, B24, C24, YE2T4);
//Declaración Operadores Lógicos
  Ejer1Tabla1 OP1(A11, B11, C11, YE1T1);
  Ejer1Tabla2 OP2(A12, B12, C12, YE1T2);
  Ejer1Tabla3 OP3(A13, B13, C13, D13, YE1T3);
  Ejer1Tabla4 OP4(A14, B14, C14, D14, YE1T4);

//Gate Level Modelling
//Ejercicio 2 Tabla 1
  initial begin
	#3
    $display("\n");
	$display("Ejercicio 2, Tabla 1");
    $display("A B C D | Y");
    $display("--------|--");
    $monitor("%b %b %b %b | %b", A21, B21, C21, D21, YE2T1);
       A21 = 0; B21 = 0; C21 = 0; D21 = 0;
    #1 A21 = 0; B21 = 0; C21 = 0; D21 = 1;
    #1 A21 = 0; B21 = 0; C21 = 1; D21 = 0;
    #1 A21 = 0; B21 = 0; C21 = 1; D21 = 1;
    #1 A21 = 0; B21 = 1; C21 = 0; D21 = 0;
    #1 A21 = 0; B21 = 1; C21 = 0; D21 = 1;
    #1 A21 = 0; B21 = 1; C21 = 1; D21 = 0;
    #1 A21 = 0; B21 = 1; C21 = 1; D21 = 1;
	#1 A21 = 1; B21 = 0; C21 = 0; D21 = 0;
	#1 A21 = 1; B21 = 0; C21 = 0; D21 = 1;
	#1 A21 = 1; B21 = 0; C21 = 1; D21 = 0;
	#1 A21 = 1; B21 = 0; C21 = 1; D21 = 1;
	#1 A21 = 1; B21 = 1; C21 = 0; D21 = 0;
	#1 A21 = 1; B21 = 1; C21 = 0; D21 = 1;
	#1 A21 = 1; B21 = 1; C21 = 1; D21 = 0;
	#1 A21 = 1; B21 = 1; C21 = 1; D21 = 1;
  end
  
  
  //Ejercicio 2 Tabla 2
    initial begin
	#20
	$display("\n");
	$display("Ejercicio 2, Tabla 2");
    $display("A B C | Y");
    $display("------|--");
    $monitor("%b %b %b | %b", A22, B22, C22, YE2T2);
       A22 = 0; B22 = 0; C22 = 0;
    #1 A22 = 0; B22 = 0; C22 = 1;
    #1 A22 = 0; B22 = 1; C22 = 0;
    #1 A22 = 0; B22	= 1; C22 = 1;
    #1 A22 = 1; B22 = 0; C22 = 0;
    #1 A22 = 1; B22 = 0; C22 = 1;
    #1 A22 = 1; B22 = 1; C22 = 0;
    #1 A22 = 1; B22 = 1; C22 = 1;
  end
  
  
 //Ejercicio 2 Tabla 3
   initial begin
   #29
    $display("\n");
	$display("Ejercicio 2, Tabla 3");
    $display("A B C D | Y");
    $display("--------|--");
    $monitor("%b %b %b %b | %b", A23, B23, C23, D23, YE2T3);
       A23 = 0; B23 = 0; C23 = 0; D23 = 0;
    #1 A23 = 0; B23 = 0; C23 = 0; D23 = 1;
    #1 A23 = 0; B23 = 0; C23 = 1; D23 = 0;
    #1 A23 = 0; B23 = 0; C23 = 1; D23 = 1;
    #1 A23 = 0; B23 = 1; C23 = 0; D23 = 0;
    #1 A23 = 0; B23 = 1; C23 = 0; D23 = 1;
    #1 A23 = 0; B23 = 1; C23 = 1; D23 = 0;
    #1 A23 = 0; B23 = 1; C23 = 1; D23 = 1;
	#1 A23 = 1; B23 = 0; C23 = 0; D23 = 0;
	#1 A23 = 1; B23 = 0; C23 = 0; D23 = 1;
	#1 A23 = 1; B23 = 0; C23 = 1; D23 = 0;
	#1 A23 = 1; B23 = 0; C23 = 1; D23 = 1;
	#1 A23 = 1; B23 = 1; C23 = 0; D23 = 0;
	#1 A23 = 1; B23 = 1; C23 = 0; D23 = 1;
	#1 A23 = 1; B23 = 1; C23 = 1; D23 = 0;
	#1 A23 = 1; B23 = 1; C23 = 1; D23 = 1;
  end


//Ejercicio 2 Tabla 4
  initial begin
	#45
	$display("\n");
	$display("Ejercicio 2, Tabla 4");
    $display("A B C | Y");
    $display("------|--");
    $monitor("%b %b %b | %b", A24, B24, C24, YE2T4);
       A24 = 0; B24 = 0; C24 = 0;
    #1 A24 = 0; B24 = 0; C24 = 1;
    #1 A24 = 0; B24 = 1; C24 = 0;
    #1 A24 = 0; B24	= 1; C24 = 1;
    #1 A24 = 1; B24 = 0; C24 = 0;
    #1 A24 = 1; B24 = 0; C24 = 1;
    #1 A24 = 1; B24 = 1; C24 = 0;
    #1 A24 = 1; B24 = 1; C24 = 1;
  end
  

// Operadores Lógicos
//Ejercicio 1 Tabla 1
  initial begin
    #54
    $display("\n");
	$display("Ejercicio 1, Tabla 1");
    $display("A B C | Y");
    $display("------|--");
    $monitor("%b %b %b | %b", A11, B11, C11, YE1T1);
       A11 = 0; B11 = 0; C11 = 0;
    #1 A11 = 0; B11 = 0; C11 = 1;
    #1 A11 = 0; B11 = 1; C11 = 0;
    #1 A11 = 0; B11 = 1; C11 = 1;
    #1 A11 = 1; B11 = 0; C11 = 0;
    #1 A11 = 1; B11 = 0; C11 = 1;
    #1 A11 = 1; B11 = 1; C11 = 0;
    #1 A11 = 1; B11 = 1; C11 = 1;
  end


//Ejercicio 1 Tabla 2
  initial begin
    #63
    $display("\n");
	$display("Ejercicio 1, Tabla 2");
    $display("A B C | Y");
    $display("------|--");
    $monitor("%b %b %b | %b", A12, B12, C12, YE1T2);
       A12 = 0; B12 = 0; C12 = 0;
    #1 A12 = 0; B12 = 0; C12 = 1;
    #1 A12 = 0; B12 = 1; C12 = 0;
    #1 A12 = 0; B12 = 1; C12 = 1;
    #1 A12 = 1; B12 = 0; C12 = 0;
    #1 A12 = 1; B12 = 0; C12 = 1;
    #1 A12 = 1; B12 = 1; C12 = 0;
    #1 A12 = 1; B12 = 1; C12 = 1;
  end
  

//Ejercicio 1 Tabla 3
  initial begin
    #72
    $display("\n");
	$display("Ejercicio 1, Tabla 3");
    $display("A B C D | Y");
    $display("--------|--");
    $monitor("%b %b %b %b | %b", A13, B13, C13, D13, YE1T3);
       A13 = 0; B13 = 0; C13 = 0; D13 = 0;
    #1 A13 = 0; B13 = 0; C13 = 0; D13 = 1;
    #1 A13 = 0; B13 = 0; C13 = 1; D13 = 0;
    #1 A13 = 0; B13 = 0; C13 = 1; D13 = 1;
    #1 A13 = 0; B13 = 1; C13 = 0; D13 = 0;
    #1 A13 = 0; B13 = 1; C13 = 0; D13 = 1;
    #1 A13 = 0; B13 = 1; C13 = 1; D13 = 0;
    #1 A13 = 0; B13 = 1; C13 = 1; D13 = 1;
	#1 A13 = 1; B13 = 0; C13 = 0; D13 = 0;
	#1 A13 = 1; B13 = 0; C13 = 0; D13 = 1;
	#1 A13 = 1; B13 = 0; C13 = 1; D13 = 0;
	#1 A13 = 1; B13 = 0; C13 = 1; D13 = 1;
	#1 A13 = 1; B13 = 1; C13 = 0; D13 = 0;
	#1 A13 = 1; B13 = 1; C13 = 0; D13 = 1;
	#1 A13 = 1; B13 = 1; C13 = 1; D13 = 0;
	#1 A13 = 1; B13 = 1; C13 = 1; D13 = 1;
  end
  
  
//Ejercicio 1 Tabla 4
  initial begin
    #89
    $display("\n");
	$display("Ejercicio 1, Tabla 4");
    $display("A B C D | Y");
    $display("--------|--");
    $monitor("%b %b %b %b | %b", A14, B14, C14, D14, YE1T4);
       A14 = 0; B14 = 0; C14 = 0; D14 = 0;
    #1 A14 = 0; B14 = 0; C14 = 0; D14 = 1;
    #1 A14 = 0; B14 = 0; C14 = 1; D14 = 0;
    #1 A14 = 0; B14 = 0; C14 = 1; D14 = 1;
    #1 A14 = 0; B14 = 1; C14 = 0; D14 = 0;
    #1 A14 = 0; B14 = 1; C14 = 0; D14 = 1;
    #1 A14 = 0; B14 = 1; C14 = 1; D14 = 0;
    #1 A14 = 0; B14 = 1; C14 = 1; D14 = 1;
	#1 A14 = 1; B14 = 0; C14 = 0; D14 = 0;
	#1 A14 = 1; B14 = 0; C14 = 0; D14 = 1;
	#1 A14 = 1; B14 = 0; C14 = 1; D14 = 0;
	#1 A14 = 1; B14 = 0; C14 = 1; D14 = 1;
	#1 A14 = 1; B14 = 1; C14 = 0; D14 = 0;
	#1 A14 = 1; B14 = 1; C14 = 0; D14 = 1;
	#1 A14 = 1; B14 = 1; C14 = 1; D14 = 0;
	#1 A14 = 1; B14 = 1; C14 = 1; D14 = 1;
  end

  

  initial
    #107 $finish;
  
  initial begin
    $dumpfile("codigoEjercicio4_tb.vcd");
    $dumpvars(0, testbench);
  end
  
endmodule

LAB/LAB 4/ejercicio 4/codigoEjercicio4_tb.vcd
$date
	Fri Sep 04 17:20:07 2020
$end
$version
	Icarus Verilog
$end
$timescale
	1ps
$end
$scope module testbench $end
$var wire 1 ! YE2T4 $end
$var wire 1 " YE2T3 $end
$var wire 1 # YE2T2 $end
$var wire 1 $ YE2T1 $end
$var wire 1 % YE1T4 $end
$var wire 1 & YE1T3 $end
$var wire 1 ' YE1T2 $end
$var wire 1 ( YE1T1 $end
$var reg 1 ) A11 $end
$var reg 1 * A12 $end
$var reg 1 + A13 $end
$var reg 1 , A14 $end
$var reg 1 - A21 $end
$var reg 1 . A22 $end
$var reg 1 / A23 $end
$var reg 1 0 A24 $end
$var reg 1 1 B11 $end
$var reg 1 2 B12 $end
$var reg 1 3 B13 $end
$var reg 1 4 B14 $end
$var reg 1 5 B21 $end
$var reg 1 6 B22 $end
$var reg 1 7 B23 $end
$var reg 1 8 B24 $end
$var reg 1 9 C11 $end
$var reg 1 : C12 $end
$var reg 1 ; C13 $end
$var reg 1 < C14 $end
$var reg 1 = C21 $end
$var reg 1 > C22 $end
$var reg 1 ? C23 $end
$var reg 1 @ C24 $end
$var reg 1 A D13 $end
$var reg 1 B D14 $end
$var reg 1 C D21 $end
$var reg 1 D D23 $end
$scope module G1 $end
$var wire 1 - A $end
$var wire 1 E A1 $end
$var wire 1 F A2 $end
$var wire 1 G A3 $end
$var wire 1 H A4 $end
$var wire 1 5 B $end
$var wire 1 = C $end
$var wire 1 C D $end
$var wire 1 I NB $end
$var wire 1 J NC $end
$var wire 1 K ND $end
$var wire 1 $ Y $end
$upscope $end
$scope module G2 $end
$var wire 1 . A $end
$var wire 1 6 B $end
$var wire 1 > C $end
$var wire 1 L NB $end
$var wire 1 # Y $end
$upscope $end
$scope module G3 $end
$var wire 1 / A $end
$var wire 1 M A1 $end
$var wire 1 N A2 $end
$var wire 1 7 B $end
$var wire 1 ? C $end
$var wire 1 D D $end
$var wire 1 O NC $end
$var wire 1 " Y $end
$upscope $end
$scope module G4 $end
$var wire 1 0 A $end
$var wire 1 P A1 $end
$var wire 1 8 B $end
$var wire 1 @ C $end
$var wire 1 Q NA $end
$var wire 1 R NC $end
$var wire 1 ! Y $end
$upscope $end
$scope module OP1 $end
$var wire 1 ) A $end
$var wire 1 1 B $end
$var wire 1 9 C $end
$var wire 1 ( Y $end
$upscope $end
$scope module OP2 $end
$var wire 1 * A $end
$var wire 1 2 B $end
$var wire 1 : C $end
$var wire 1 ' Y $end
$upscope $end
$scope module OP3 $end
$var wire 1 + A $end
$var wire 1 3 B $end
$var wire 1 ; C $end
$var wire 1 A D $end
$var wire 1 & Y $end
$upscope $end
$scope module OP4 $end
$var wire 1 , A $end
$var wire 1 4 B $end
$var wire 1 < C $end
$var wire 1 B D $end
$var wire 1 % Y $end
$upscope $end
$upscope $end
$enddefinitions $end
#0
$dumpvars
xR
xQ
xP
xO
xN
xM
xL
xK
xJ
xI
xH
xG
xF
xE
xD
xC
xB
xA
x@
x?
x>
x=
x<
x;
x:
x9
x8
x7
x6
x5
x4
x3
x2
x1
x0
x/
x.
x-
x,
x+
x*
x)
x(
x'
x&
x%
x$
x#
x"
x!
$end
#3
1$
1H
1K
1J
1I
0E
0F
0G
0C
0=
05
0-
#4
0$
0H
0K
1C
#5
1K
0J
0C
1=
#6
0K
1C
#7
1K
1J
0I
0C
0=
15
#8
0K
1C
#9
1K
0J
0C
1=
#10
0K
1C
#11
1$
1G
1F
1E
1H
1K
1J
1I
0C
0=
05
1-
#12
0G
0H
0K
1C
#13
1G
0F
1K
0J
0C
1=
#14
0G
0K
1C
#15
1G
1F
0E
1K
1J
0I
0C
0=
15
#16
0G
0K
1C
#17
1G
0F
1K
0J
0C
1=
#18
0$
0G
0K
1C
#20
1#
1L
0>
06
0.
#21
1>
#22
0#
0L
0>
16
#23
1#
1>
#24
1L
0>
06
1.
#25
1>
#26
0#
0L
0>
16
#27
1#
1>
#29
0"
0M
1O
0N
0D
0?
07
0/
#30
1"
1M
1D
#31
0"
0M
0O
0D
1?
#32
1D
#33
1O
1"
0D
0?
17
#34
1M
1D
#35
0M
0O
0D
1?
#36
1D
#37
1O
0"
0D
0?
07
1/
#38
1"
1M
1N
1D
#39
0"
0M
0N
0O
0D
1?
#40
1"
1N
1D
#41
0N
1O
0D
0?
17
#42
1M
1N
1D
#43
0M
0N
0O
0D
1?
#44
1N
1D
#45
1!
1P
1R
1Q
0@
08
00
#46
0!
0P
0R
1@
#47
1P
1R
1!
0@
18
#48
0P
0R
1@
#49
1R
0!
0Q
0@
08
10
#50
0R
1@
#51
1R
1!
0@
18
#52
0R
1@
#54
1(
09
01
0)
#55
0(
19
#56
1(
09
11
#57
0(
19
#58
1(
09
01
1)
#59
19
#60
0(
09
11
#61
1(
19
#63
1'
0:
02
0*
#64
1:
#65
0'
0:
12
#66
1:
#67
1'
0:
02
1*
#68
1:
#69
0'
0:
12
#70
1:
#72
1&
0A
0;
03
0+
#73
0&
1A
#74
0A
1;
#75
1&
1A
#76
0&
0A
0;
13
#77
1&
1A
#78
0A
1;
#79
0&
1A
#80
0A
0;
03
1+
#81
1&
1A
#82
0A
1;
#83
0&
1A
#84
1&
0A
0;
13
#85
0&
1A
#86
0A
1;
#87
1&
1A
#89
0%
0B
0<
04
0,
#90
1B
#91
0B
1<
#92
1B
#93
0B
0<
14
#94
1B
#95
0B
1<
#96
1B
#97
1%
0B
0<
04
1,
#98
0%
1B
#99
1%
0B
1<
#100
1B
#101
0B
0<
14
#102
1B
#103
0B
1<
#104
1B
