LAB/LAB 9/Ejercicio 4/ejercicio4.v
//Ejercicio 4


//modulo Buffer Tri-estado
module BufTri(input wire enable, input wire [3:0]IN, output wire [3:0]OUT);
	assign OUT = enable ? IN : 4'bz;
endmodule

LAB/LAB 9/Ejercicio 4/ejercicio4_tb.v
module Ejercicio_4();

  reg [3:0]IN; reg enable; 
  wire [3:0]OUT; 

//Variables para módulo
	BufTri U4(enable, IN, OUT);


//Prueba para Buffer
  initial begin
	#3
    $display("\n");
	$display("Ejercicio 4");
    $display("E IN | OUT");
    $display("-----------------");
    $monitor("%b %b | %b", enable, IN, OUT);
       enable = 0; IN = 1;
    #1 enable = 1;
	#10 enable = 0;
	#5 IN = 5;
	#5 IN = 15;
	#5 enable = 1;
	#5 IN = 3;
	#5 IN = 6;
	#5 enable = 0;

  end

	initial
    #50 $finish;
  initial begin
    $dumpfile("ejercicio4_tb.vcd");
    $dumpvars(0, Ejercicio_4);
  end
endmodule

LAB/LAB 9/Ejercicio 4/ejercicio4_tb.vcd
$date
	Fri Oct 30 16:48:41 2020
$end
$version
	Icarus Verilog
$end
$timescale
	1ps
$end
$scope module Ejercicio_4 $end
$var wire 4 ! OUT [3:0] $end
$var reg 4 " IN [3:0] $end
$var reg 1 # enable $end
$scope module U4 $end
$var wire 4 $ IN [3:0] $end
$var wire 1 # enable $end
$var wire 4 % OUT [3:0] $end
$upscope $end
$upscope $end
$enddefinitions $end
#0
$dumpvars
bx %
bx $
x#
bx "
bx !
$end
#3
bz !
bz %
b1 "
b1 $
0#
#4
b1 !
b1 %
1#
#14
bz !
bz %
0#
#19
b101 "
b101 $
#24
b1111 "
b1111 $
#29
b1111 !
b1111 %
1#
#34
b11 !
b11 %
b11 "
b11 $
#39
b110 !
b110 %
b110 "
b110 $
#44
bz !
bz %
0#
