LAB/LAB 10/Ejercicio 1/ejercicio1Lab10.v
//Ejercicio 1

//Program Counter
module CounterLoad(input wire [11:0]data, input wire load, enable, clk, reset, output reg [11:0]out);
	always @(posedge clk or posedge load or posedge reset)
		if (reset) begin
			out <= 12'b0 ;
		end else if (load) begin
			out <= data;
		end else if (enable) begin
			out <= out + 1;
		end
endmodule 


//Memoria ROM
module MemoriaRom (input wire [11:0]address, output wire [7:0]data);           
	reg [11:0] mem [0:4095] ;  
    
	assign data = mem[address];

initial begin
  $readmemb("memoria.txt", mem); 
end

endmodule


//Fetch
module Fetch(input wire CLK, input wire [7:0]D, input wire reset, input wire enable, output [3:0]Q1, output [3:0]Q0);
reg Q1;
reg Q0;
wire [3:0]D1;
wire [3:0]D0;
assign D1[0] = D[4];
assign D1[1] = D[5];
assign D1[2] = D[6];
assign D1[3] = D[7];
assign D0[0] = D[0];
assign D0[1] = D[1];
assign D0[2] = D[2];
assign D0[3] = D[3];
	always @(posedge CLK or	posedge reset or posedge enable)
		if (reset)begin
		Q1 <= 0;
		Q0 <= 0;
	end else if(enable) begin
		Q1 <= D1;
		Q0 <= D0;
	end
endmodule


module Ejer1 (input wire load, clk, enable1, enable2, reset, input wire [11:0]data, output wire [3:0]Q1, output wire [3:0]Q0);
	wire [11:0]OutCL;
	wire [7:0]OutMR;
	CounterLoad O1(data, load,  enable1, clk, reset, OutCL);
	MemoriaRom O2(OutCL, OutMR);
	Fetch O3(clk, OutMR, reset, enable2, Q1, Q0);
endmodule

LAB/LAB 10/Ejercicio 1/ejercicio1Lab10_tb.v
module Ejercicio_1LAB10();

  reg Clk, reset, enable1, enable2, load; reg [11:0]data; 
  wire [3:0]Q1; wire [3:0]Q2;

//Variables para módulo
	Ejer1 U1(load, Clk, enable1, enable2, reset, data, Q1, Q2);


//Prueba para FLipFlop de 1 bit
initial begin
	Clk=0;
	forever #5 Clk = ~Clk;
end
  initial begin
	#3
    $display("\n");
	$display("         EJERCICIO 1\n");
    $display("CLK E R L      D       |  Q1    Q0");
    $display("------------------------------------");
    $monitor("%b   %b %b %b %b %b | %b  %b", Clk, enable1, enable2, reset, load, data, Q1, Q2);
	//es escogieron números aleatorios para A
       reset = 1; enable1 = 0; enable2 = 0; load = 0; data = 0;
    #1 reset = 0;
	#20 enable1 = 1; enable2 = 1;
	#50 data = 50; load = 1;
	#15 load = 0;
	#15 load = 0;
  end




	initial
    #150 $finish;
  initial begin
    $dumpfile("ejercicio1Lab10_tb.vcd");
    $dumpvars(0, Ejercicio_1LAB10);
  end
endmodule

LAB/LAB 10/Ejercicio 1/ejercicio1Lab10_tb.vcd
$date
	Thu Nov 05 18:45:59 2020
$end
$version
	Icarus Verilog
$end
$timescale
	1ps
$end
$scope module Ejercicio_1LAB10 $end
$var wire 4 ! Q2 [3:0] $end
$var wire 4 " Q1 [3:0] $end
$var reg 1 # Clk $end
$var reg 12 $ data [11:0] $end
$var reg 1 % enable1 $end
$var reg 1 & enable2 $end
$var reg 1 ' load $end
$var reg 1 ( reset $end
$scope module U1 $end
$var wire 1 # clk $end
$var wire 12 ) data [11:0] $end
$var wire 1 % enable1 $end
$var wire 1 & enable2 $end
$var wire 1 ' load $end
$var wire 1 ( reset $end
$var wire 4 * Q1 [3:0] $end
$var wire 4 + Q0 [3:0] $end
$var wire 8 , OutMR [7:0] $end
$var wire 12 - OutCL [11:0] $end
$scope module O1 $end
$var wire 1 # clk $end
$var wire 12 . data [11:0] $end
$var wire 1 % enable $end
$var wire 1 ' load $end
$var wire 1 ( reset $end
$var reg 12 / out [11:0] $end
$upscope $end
$scope module O2 $end
$var wire 12 0 address [11:0] $end
$var wire 8 1 data [7:0] $end
$upscope $end
$scope module O3 $end
$var wire 1 # CLK $end
$var wire 8 2 D [7:0] $end
$var wire 1 & enable $end
$var wire 1 ( reset $end
$var wire 4 3 D1 [3:0] $end
$var wire 4 4 D0 [3:0] $end
$var reg 4 5 Q0 [3:0] $end
$var reg 4 6 Q1 [3:0] $end
$upscope $end
$upscope $end
$upscope $end
$enddefinitions $end
#0
$dumpvars
bx 6
bx 5
bx 4
bx 3
bx 2
bx 1
bx 0
bx /
bx .
bx -
bx ,
bx +
bx *
bx )
x(
x'
x&
x%
bx $
0#
bx "
bx !
$end
#3
b0 3
b0 4
b0 ,
b0 1
b0 2
b0 -
b0 /
b0 0
b0 !
b0 +
b0 5
b0 "
b0 *
b0 6
b0 $
b0 )
b0 .
0'
0&
0%
1(
#4
0(
#5
1#
#10
0#
#15
1#
#20
0#
#24
1&
1%
#25
b1 4
b1 ,
b1 1
b1 2
b1 -
b1 /
b1 0
1#
#30
0#
#35
b10 4
b10 ,
b10 1
b10 2
b10 -
b10 /
b10 0
b1 !
b1 +
b1 5
1#
#40
0#
#45
b11 4
b11 ,
b11 1
b11 2
b11 -
b11 /
b11 0
b10 !
b10 +
b10 5
1#
#50
0#
#55
b100 4
b100 ,
b100 1
b100 2
b100 -
b100 /
b100 0
b11 !
b11 +
b11 5
1#
#60
0#
#65
b101 4
b101 ,
b101 1
b101 2
b101 -
b101 /
b101 0
b100 !
b100 +
b100 5
1#
#70
0#
#74
b11 3
b10 4
b110010 ,
b110010 1
b110010 2
b110010 -
b110010 /
b110010 0
1'
b110010 $
b110010 )
b110010 .
#75
b10 !
b10 +
b10 5
b11 "
b11 *
b11 6
1#
#80
0#
#85
1#
#89
0'
#90
0#
#95
b11 4
b110011 ,
b110011 1
b110011 2
b110011 -
b110011 /
b110011 0
1#
#100
0#
#105
b100 4
b110100 ,
b110100 1
b110100 2
b110100 -
b110100 /
b110100 0
b11 !
b11 +
b11 5
1#
#110
0#
#115
b101 4
b110101 ,
b110101 1
b110101 2
b110101 -
b110101 /
b110101 0
b100 !
b100 +
b100 5
1#
#120
0#
#125
b0 3
b1 4
b1 ,
b1 1
b1 2
b110110 -
b110110 /
b110110 0
b101 !
b101 +
b101 5
1#
#130
0#
#135
b110111 -
b110111 /
b110111 0
b1 !
b1 +
b1 5
b0 "
b0 *
b0 6
1#
#140
0#
#145
b11 3
b1000 4
b111000 ,
b111000 1
b111000 2
b111000 -
b111000 /
b111000 0
1#
