LAB/LAB 5/Ejercicio4.v


//módulo Mux 2:1
module Mux21(input logic D0, D1, S0, output wire Y);
	
	assign Y = S0 ? D1 : D0;
	
endmodule


//módulo Mux 4:1
module Mux41(input logic D0, D1, D2, D3, S0, S1, output wire Y);
	
	wire Y1, Y2;
	Mux21 E1(D0, D1, S1, Y1);
	Mux21 E3(D2, D3, S1, Y2);
	Mux21 E2(Y1, Y2 , S0, Y);
	
endmodule


//módulo Mux 8:1
module Mux81(input logic D0, D1, D2, D3, D4, D5, D6, D7, S0, S1, S2, output wire Y);

	wire Y1, Y2;
	Mux41 H1(D0, D1, D2, D3, S2, S1, Y1);
	Mux41 H2(D4, D5, D6, D7, S2, S1, Y2);
	Mux21 H3(Y1, Y2, S0, Y);
	
endmodule


//Tabla1 Mux 2:1
module Tabla1Mux21(input wire A, B, C, output wire Y);
	
	Mux21 U12(B^C,B~^C, A, Y);
	
endmodule


//Tabla 1 Mux 4:1
module Tabla1Mux41(input wire A, B, C, output wire Y);

	Mux41 U14(C, ~C, ~C, C, A, B, Y);
	
endmodule


//Tabla 1 Mux 8:1
module Tabla1Mux81(input wire A, B, C, output wire Y);

	wire V, T;
	assign V = 1;
	assign T = 0;
	Mux81 U18(T, V, V, T, V, T, T, V, A, B, C, Y);
	
endmodule


//Tabla2 Mux 2:1
module Tabla2Mux21(input wire A, B, C, output wire Y);
	
	Mux21 N12(~(B|C), ~(B&C), A, Y);
	
endmodule


//Tabla 2 Mux 4:1
module Tabla2Mux41(input wire A, B, C, output wire Y);

	Mux41 N14(~C, ~C&C, ~C|C, ~C, A, B, Y);
	
endmodule


//Tabla 2 Mux 8:1
module Tabla2Mux81(input wire A, B, C, output wire Y);

	wire V, T;
	assign V = 1;
	assign T = 0;
	Mux81 N18(V, T, T, T, V, V, V, T, A, B, C, Y);
	
endmodule

LAB/LAB 5/Ejercicio4_tb.v
module testbench();

//   | Var ejer1T1  |  Var ejer1T2 |    Var ejer1T3    |    Var ejer1T4   |    Var ejer2T1    |  Var ejer2T2  |    Var ejer2T3   | Var ejer2T4 | 
  reg A21, B21, C21, A41, B41, C41, A81, B81, C81, A22, B22, C22, A42, B42, C42, A82, B82, C82;
  wire Tabla1MUX2_1, Tabla1MUX4_1, Tabla1MUX8_1, Tabla2MUX2_1, Tabla2MUX4_1, Tabla2MUX8_1;

//Declaración Gate Level Modelling
	Tabla1Mux21 T12(A21, B21, C21, Tabla1MUX2_1);
	Tabla1Mux41 T14(A41, B41, C41, Tabla1MUX4_1);
	Tabla1Mux81 T18(A81, B81, C81, Tabla1MUX8_1);
	Tabla2Mux21 T22(A22, B22, C22, Tabla2MUX2_1);
	Tabla2Mux41 T24(A42, B42, C42, Tabla2MUX4_1);
	Tabla2Mux81 T28(A82, B82, C82, Tabla2MUX8_1);

//Tabla 1 MUX 2:1
  initial begin
	#3
    $display("\n");
	$display("Tabla 1 con MUX 2:1");
    $display("A B C | Y");
    $display("------|--");
    $monitor("%b %b %b | %b", A21, B21, C21, Tabla1MUX2_1);
       A21 = 0; B21 = 0; C21 = 0;
    #1 A21 = 0; B21 = 0; C21 = 1;
    #1 A21 = 0; B21 = 1; C21 = 0;
    #1 A21 = 0; B21	= 1; C21 = 1;
    #1 A21 = 1; B21 = 0; C21 = 0;
    #1 A21 = 1; B21 = 0; C21 = 1;
    #1 A21 = 1; B21 = 1; C21 = 0;
    #1 A21 = 1; B21 = 1; C21 = 1;
  end
  
  
//Tabla 1 MUX 4:1
  initial begin
	#12
    $display("\n");
	$display("Tabla 1 con MUX 4:1");
    $display("A B C | Y");
    $display("------|--");
    $monitor("%b %b %b | %b", A41, B41, C41, Tabla1MUX4_1);
       A41 = 0; B41 = 0; C41 = 0;
    #1 A41 = 0; B41 = 0; C41 = 1;
    #1 A41 = 0; B41 = 1; C41 = 0;
    #1 A41 = 0; B41	= 1; C41 = 1;
    #1 A41 = 1; B41 = 0; C41 = 0;
    #1 A41 = 1; B41 = 0; C41 = 1;
    #1 A41 = 1; B41 = 1; C41 = 0;
    #1 A41 = 1; B41 = 1; C41 = 1;
  end
  
//Tabla 1 MUX 8:1
  initial begin
	#21
    $display("\n");
	$display("Tabla 1 con MUX 8:1");
    $display("A B C | Y");
    $display("------|--");
    $monitor("%b %b %b | %b", A81, B81, C81, Tabla1MUX8_1);
       A81 = 0; B81 = 0; C81 = 0;
    #1 A81 = 0; B81 = 0; C81 = 1;
    #1 A81 = 0; B81 = 1; C81 = 0;
    #1 A81 = 0; B81	= 1; C81 = 1;
    #1 A81 = 1; B81 = 0; C81 = 0;
    #1 A81 = 1; B81 = 0; C81 = 1;
    #1 A81 = 1; B81 = 1; C81 = 0;
    #1 A81 = 1; B81 = 1; C81 = 1;
  end
  
  
//Tabla 2 MUX 2:1
  initial begin
	#30
    $display("\n");
	$display("Tabla 2 con MUX 2:1");
    $display("A B C | Y");
    $display("------|--");
    $monitor("%b %b %b | %b", A22, B22, C22, Tabla2MUX2_1);
       A22 = 0; B22 = 0; C22 = 0;
    #1 A22 = 0; B22 = 0; C22 = 1;
    #1 A22 = 0; B22 = 1; C22 = 0;
    #1 A22 = 0; B22	= 1; C22 = 1;
    #1 A22 = 1; B22 = 0; C22 = 0;
    #1 A22 = 1; B22 = 0; C22 = 1;
    #1 A22 = 1; B22 = 1; C22 = 0;
    #1 A22 = 1; B22 = 1; C22 = 1;
  end
  
  
//Tabla 2 MUX 4:1
  initial begin
	#39
    $display("\n");
	$display("Tabla 2 con MUX 4:1");
    $display("A B C | Y");
    $display("------|--");
    $monitor("%b %b %b | %b", A42, B42, C42, Tabla2MUX4_1);
       A42 = 0; B42 = 0; C42 = 0;
    #1 A42 = 0; B42 = 0; C42 = 1;
    #1 A42 = 0; B42 = 1; C42 = 0;
    #1 A42 = 0; B42	= 1; C42 = 1;
    #1 A42 = 1; B42 = 0; C42 = 0;
    #1 A42 = 1; B42 = 0; C42 = 1;
    #1 A42 = 1; B42 = 1; C42 = 0;
    #1 A42 = 1; B42 = 1; C42 = 1;
  end
  
  
//Tabla 2 MUX 8:1
  initial begin
	#48
    $display("\n");
	$display("Tabla 2 con MUX 8:1");
    $display("A B C | Y");
    $display("------|--");
    $monitor("%b %b %b | %b", A82, B82, C82, Tabla2MUX8_1);
       A82 = 0; B82 = 0; C82 = 0;
    #1 A82 = 0; B82 = 0; C82 = 1;
    #1 A82 = 0; B82 = 1; C82 = 0;
    #1 A82 = 0; B82	= 1; C82 = 1;
    #1 A82 = 1; B82 = 0; C82 = 0;
    #1 A82 = 1; B82 = 0; C82 = 1;
    #1 A82 = 1; B82 = 1; C82 = 0;
    #1 A82 = 1; B82 = 1; C82 = 1;
  end
  
  
  initial
    #64 $finish;

  initial begin
    $dumpfile("Ejercicio4_tb.vcd");
    $dumpvars(0, testbench);
  end
  
  
endmodule

LAB/LAB 5/Ejercicio4_tb.vcd
$date
	Thu Aug 13 21:52:47 2020
$end
$version
	Icarus Verilog
$end
$timescale
	1ps
$end
$scope module testbench $end
$var wire 1 ! Tabla2MUX8_1 $end
$var wire 1 " Tabla2MUX4_1 $end
$var wire 1 # Tabla2MUX2_1 $end
$var wire 1 $ Tabla1MUX8_1 $end
$var wire 1 % Tabla1MUX4_1 $end
$var wire 1 & Tabla1MUX2_1 $end
$var reg 1 ' A21 $end
$var reg 1 ( A22 $end
$var reg 1 ) A41 $end
$var reg 1 * A42 $end
$var reg 1 + A81 $end
$var reg 1 , A82 $end
$var reg 1 - B21 $end
$var reg 1 . B22 $end
$var reg 1 / B41 $end
$var reg 1 0 B42 $end
$var reg 1 1 B81 $end
$var reg 1 2 B82 $end
$var reg 1 3 C21 $end
$var reg 1 4 C22 $end
$var reg 1 5 C41 $end
$var reg 1 6 C42 $end
$var reg 1 7 C81 $end
$var reg 1 8 C82 $end
$scope module T12 $end
$var wire 1 ' A $end
$var wire 1 - B $end
$var wire 1 3 C $end
$var wire 1 & Y $end
$scope module U12 $end
$var wire 1 9 D0 $end
$var wire 1 : D1 $end
$var wire 1 ' S0 $end
$var wire 1 & Y $end
$upscope $end
$upscope $end
$scope module T14 $end
$var wire 1 ) A $end
$var wire 1 / B $end
$var wire 1 5 C $end
$var wire 1 % Y $end
$scope module U14 $end
$var wire 1 5 D0 $end
$var wire 1 ; D1 $end
$var wire 1 < D2 $end
$var wire 1 5 D3 $end
$var wire 1 ) S0 $end
$var wire 1 / S1 $end
$var wire 1 = Y2 $end
$var wire 1 > Y1 $end
$var wire 1 % Y $end
$scope module E1 $end
$var wire 1 5 D0 $end
$var wire 1 ; D1 $end
$var wire 1 / S0 $end
$var wire 1 > Y $end
$upscope $end
$scope module E2 $end
$var wire 1 > D0 $end
$var wire 1 ) S0 $end
$var wire 1 % Y $end
$var wire 1 = D1 $end
$upscope $end
$scope module E3 $end
$var wire 1 < D0 $end
$var wire 1 5 D1 $end
$var wire 1 / S0 $end
$var wire 1 = Y $end
$upscope $end
$upscope $end
$upscope $end
$scope module T18 $end
$var wire 1 + A $end
$var wire 1 1 B $end
$var wire 1 7 C $end
$var wire 1 ? T $end
$var wire 1 @ V $end
$var wire 1 $ Y $end
$scope module U18 $end
$var wire 1 ? D0 $end
$var wire 1 @ D1 $end
$var wire 1 @ D2 $end
$var wire 1 ? D3 $end
$var wire 1 @ D4 $end
$var wire 1 ? D5 $end
$var wire 1 ? D6 $end
$var wire 1 @ D7 $end
$var wire 1 + S0 $end
$var wire 1 1 S1 $end
$var wire 1 7 S2 $end
$var wire 1 A Y2 $end
$var wire 1 B Y1 $end
$var wire 1 $ Y $end
$scope module H1 $end
$var wire 1 ? D0 $end
$var wire 1 @ D1 $end
$var wire 1 @ D2 $end
$var wire 1 ? D3 $end
$var wire 1 7 S0 $end
$var wire 1 1 S1 $end
$var wire 1 C Y2 $end
$var wire 1 D Y1 $end
$var wire 1 B Y $end
$scope module E1 $end
$var wire 1 ? D0 $end
$var wire 1 @ D1 $end
$var wire 1 1 S0 $end
$var wire 1 D Y $end
$upscope $end
$scope module E2 $end
$var wire 1 D D0 $end
$var wire 1 7 S0 $end
$var wire 1 B Y $end
$var wire 1 C D1 $end
$upscope $end
$scope module E3 $end
$var wire 1 @ D0 $end
$var wire 1 ? D1 $end
$var wire 1 1 S0 $end
$var wire 1 C Y $end
$upscope $end
$upscope $end
$scope module H2 $end
$var wire 1 @ D0 $end
$var wire 1 ? D1 $end
$var wire 1 ? D2 $end
$var wire 1 @ D3 $end
$var wire 1 7 S0 $end
$var wire 1 1 S1 $end
$var wire 1 E Y2 $end
$var wire 1 F Y1 $end
$var wire 1 A Y $end
$scope module E1 $end
$var wire 1 @ D0 $end
$var wire 1 ? D1 $end
$var wire 1 1 S0 $end
$var wire 1 F Y $end
$upscope $end
$scope module E2 $end
$var wire 1 F D0 $end
$var wire 1 7 S0 $end
$var wire 1 A Y $end
$var wire 1 E D1 $end
$upscope $end
$scope module E3 $end
$var wire 1 ? D0 $end
$var wire 1 @ D1 $end
$var wire 1 1 S0 $end
$var wire 1 E Y $end
$upscope $end
$upscope $end
$scope module H3 $end
$var wire 1 B D0 $end
$var wire 1 A D1 $end
$var wire 1 + S0 $end
$var wire 1 $ Y $end
$upscope $end
$upscope $end
$upscope $end
$scope module T22 $end
$var wire 1 ( A $end
$var wire 1 . B $end
$var wire 1 4 C $end
$var wire 1 # Y $end
$scope module N12 $end
$var wire 1 G D0 $end
$var wire 1 H D1 $end
$var wire 1 ( S0 $end
$var wire 1 # Y $end
$upscope $end
$upscope $end
$scope module T24 $end
$var wire 1 * A $end
$var wire 1 0 B $end
$var wire 1 6 C $end
$var wire 1 " Y $end
$scope module N14 $end
$var wire 1 I D0 $end
$var wire 1 J D1 $end
$var wire 1 K D2 $end
$var wire 1 L D3 $end
$var wire 1 * S0 $end
$var wire 1 0 S1 $end
$var wire 1 M Y2 $end
$var wire 1 N Y1 $end
$var wire 1 " Y $end
$scope module E1 $end
$var wire 1 I D0 $end
$var wire 1 J D1 $end
$var wire 1 0 S0 $end
$var wire 1 N Y $end
$upscope $end
$scope module E2 $end
$var wire 1 N D0 $end
$var wire 1 * S0 $end
$var wire 1 " Y $end
$var wire 1 M D1 $end
$upscope $end
$scope module E3 $end
$var wire 1 K D0 $end
$var wire 1 L D1 $end
$var wire 1 0 S0 $end
$var wire 1 M Y $end
$upscope $end
$upscope $end
$upscope $end
$scope module T28 $end
$var wire 1 , A $end
$var wire 1 2 B $end
$var wire 1 8 C $end
$var wire 1 O T $end
$var wire 1 P V $end
$var wire 1 ! Y $end
$scope module N18 $end
$var wire 1 P D0 $end
$var wire 1 O D1 $end
$var wire 1 O D2 $end
$var wire 1 O D3 $end
$var wire 1 P D4 $end
$var wire 1 P D5 $end
$var wire 1 P D6 $end
$var wire 1 O D7 $end
$var wire 1 , S0 $end
$var wire 1 2 S1 $end
$var wire 1 8 S2 $end
$var wire 1 Q Y2 $end
$var wire 1 R Y1 $end
$var wire 1 ! Y $end
$scope module H1 $end
$var wire 1 P D0 $end
$var wire 1 O D1 $end
$var wire 1 O D2 $end
$var wire 1 O D3 $end
$var wire 1 8 S0 $end
$var wire 1 2 S1 $end
$var wire 1 S Y2 $end
$var wire 1 T Y1 $end
$var wire 1 R Y $end
$scope module E1 $end
$var wire 1 P D0 $end
$var wire 1 O D1 $end
$var wire 1 2 S0 $end
$var wire 1 T Y $end
$upscope $end
$scope module E2 $end
$var wire 1 T D0 $end
$var wire 1 8 S0 $end
$var wire 1 R Y $end
$var wire 1 S D1 $end
$upscope $end
$scope module E3 $end
$var wire 1 O D0 $end
$var wire 1 O D1 $end
$var wire 1 2 S0 $end
$var wire 1 S Y $end
$upscope $end
$upscope $end
$scope module H2 $end
$var wire 1 P D0 $end
$var wire 1 P D1 $end
$var wire 1 P D2 $end
$var wire 1 O D3 $end
$var wire 1 8 S0 $end
$var wire 1 2 S1 $end
$var wire 1 U Y2 $end
$var wire 1 V Y1 $end
$var wire 1 Q Y $end
$scope module E1 $end
$var wire 1 P D0 $end
$var wire 1 P D1 $end
$var wire 1 2 S0 $end
$var wire 1 V Y $end
$upscope $end
$scope module E2 $end
$var wire 1 V D0 $end
$var wire 1 8 S0 $end
$var wire 1 Q Y $end
$var wire 1 U D1 $end
$upscope $end
$scope module E3 $end
$var wire 1 P D0 $end
$var wire 1 O D1 $end
$var wire 1 2 S0 $end
$var wire 1 U Y $end
$upscope $end
$upscope $end
$scope module H3 $end
$var wire 1 R D0 $end
$var wire 1 Q D1 $end
$var wire 1 , S0 $end
$var wire 1 ! Y $end
$upscope $end
$upscope $end
$upscope $end
$upscope $end
$enddefinitions $end
#0
$dumpvars
1V
xU
xT
0S
xR
xQ
1P
0O
xN
xM
xL
xK
xJ
xI
xH
xG
xF
xE
xD
xC
xB
xA
1@
0?
x>
x=
x<
x;
x:
x9
x8
x7
x6
x5
x4
x3
x2
x1
x0
x/
x.
x-
x,
x+
x*
x)
x(
x'
x&
x%
x$
x#
x"
x!
$end
#3
0&
09
1:
03
0-
0'
#4
1&
19
0:
13
#5
03
1-
#6
0&
09
1:
13
#7
1&
03
0-
1'
#8
0&
19
0:
13
#9
03
1-
#10
1&
09
1:
13
#12
1=
0%
1;
1<
0>
05
0/
0)
#13
0=
1%
0;
0<
1>
15
#14
1%
1;
1<
1>
05
1/
#15
0%
0>
0;
0<
1=
15
#16
1;
1<
1=
1%
05
0/
1)
#17
0%
0=
0;
0<
1>
15
#18
1;
1<
1>
05
1/
#19
0>
1%
0;
0<
1=
15
#21
0$
0B
1A
0D
1C
1F
0E
07
01
0+
#22
1$
1B
0A
17
#23
1D
0C
0F
1E
07
11
#24
0$
0B
1A
17
#25
0D
1C
1F
0E
1$
07
01
1+
#26
0$
1B
0A
17
#27
1D
0C
0F
1E
07
11
#28
1$
0B
1A
17
#30
1#
1G
1H
04
0.
0(
#31
0#
0G
14
#32
04
1.
#33
0H
14
#34
1#
1G
1H
04
0.
1(
#35
0G
14
#36
04
1.
#37
0#
0H
14
#39
1"
1M
1N
1K
1I
0J
1L
06
00
0*
#40
0"
0N
0I
0J
0L
16
#41
1I
1K
1L
1M
06
10
#42
0"
0N
0M
0I
0J
0L
16
#43
1N
1"
1I
1K
1L
1M
06
00
1*
#44
0N
0I
0J
0L
16
#45
1"
1I
1K
1L
1M
06
10
#46
0"
0N
0M
0I
0J
0L
16
#48
1!
1R
1Q
1T
1U
08
02
0,
#49
0!
0R
18
#50
0T
0U
08
12
#51
0Q
18
#52
1!
1R
1Q
1T
1U
08
02
1,
#53
0R
18
#54
0T
0U
08
12
#55
0!
0Q
18
