LAB/LAB 8/LAB8.v
//Ejercicio 1
module CounterLoad(input wire [11:0]data, input wire load, enable, clk, reset, output reg [11:0]out);
	always @(posedge clk or posedge load or posedge reset)
		if (reset) begin
			out <= 12'b0 ;
		end else if (load) begin
			out <= data;
		end else if (enable) begin
			out <= out + 1;
		end
endmodule 


//Ejercicio 2
module MemoriaRom (input wire [11:0]address, output wire [7:0]data);           
	reg [11:0] mem [0:4095] ;  
    
	assign data = mem[address];

initial begin
  $readmemb("memoria.txt", mem); 
end

endmodule


//Ejercicio 3
module ALU (input wire [3:0]A, input wire [3:0]B, input wire [2:0]sel, output reg [3:0]Y); 
reg [4:0]X;
reg menor;
	always @ (A or B or sel) 
		case (sel) 
			0 : Y = A&B; 
			1 : Y = A | B; 
			2 : begin
				X = A + B; 
				Y[0] = X[0];
				Y[1] = X[1];
				Y[2] = X[2];
				Y[3] = X[3];
				end
			3 : Y = 0;
			4 : Y = A&~B;
			5 : Y = A | ~B;
			6 : begin
				X = A - B; 
				Y[0] = X[0];
				Y[1] = X[1];
				Y[2] = X[2];
				Y[3] = X[3];
				end
			7 : begin
				menor = (A < B);
				if (menor)begin
				Y = 4'b1111;
				end else begin
				Y = 0;
				end
				end
			default : $display("Error in SEL"); 
		endcase 
    
endmodule

LAB/LAB 8/LAB8_tb.v
module LAB_8();

  reg [11:0]data; reg[11:0]add; reg [3:0]A; reg [3:0]B; reg [2:0]sel;
  reg load, EC, reset, clk;
  wire [11:0]Contador; wire [7:0]Memoria; wire [3:0]alu;

//Variables para módulo
	CounterLoad U1(data, load, EC, clk, reset, Contador);
	MemoriaRom U2(add, Memoria);
	ALU U3(A, B, sel, alu);


//Ejercicio 1
initial begin
	clk=0;
	forever #1 clk = ~clk;
end
  initial begin
	#3
    $display("\n");
	$display("Ejercicio 1");
    $display("clk data load enable |  Contador");
    $display("--------------------------------");
    $monitor("%b  %d    %b     %b   |%d", clk, data, load, EC, Contador);
       reset = 1; data = 20; load = 0; EC = 0;
	   #1 reset = 0;
	   #5 EC = 1;
	   #20 load = 1;
	   #5 load = 0; data = 50;
	   #5 load = 1;
	   #5 load = 0;
	   #10 EC = 0;
  end
 

//Ejercicio 2
   initial begin
	#60
    $display("\n");
	$display("Ejercicio 2");
    $display("ADD  | Memoria");
    $display("--------------");
    $monitor("%d   |%d", add, Memoria);
	  #1 add = 00;
	  #2 add = 55;
	  #2 add = 80;
	  #2 add = 85;
	  #2 add = 95;
	  #2 add = 96;
	  #2 add = 13;
	  #2 add = 35;
	  #2 add = 98;
	  #2 add = 68;
  end
  

//Ejercicio 3
   initial begin
	#80
    $display("\n");
	$display("Ejercicio 2");
    $display(" A     B   Sel  | Y");
    $display("---------------------");
    $monitor("%b %b %b  |%b", A, B, sel, alu);
	sel = 0; A = 0; B = 0;
	#1 B = 1;
	#1 A = 1;
	#1 B = 15;
	#1 A = 15;
	#2 sel = 1; A = 0; B = 0;
	#1 A = 15;
	#1 A = 0;
	#1 B = 15;
	#1 A = 15;
	#2 sel = 2; A = 0; B = 0;
	#1 A = 1; B = 1;
	#1 A = 15; B = 0;
	#1 A = 7; B = 3;
	#1 A = 15; B = 1;
	#2 sel = 3;
	#1 A = 1; B = 1;
	#1 A = 15; B = 15;
	#2 sel = 4; A = 0; B = 0;
	#1 A = 15;
	#1 B = 15;
	#2 sel = 5; A = 0; B = 0;
	#1 B = 15;
	#1 A = 15;
	#1 B = 0;
	#2 sel = 6; A = 0; B = 0;
	#1 A = 10; B = 1;
	#1 A = 15; B = 10;
	#1 A = 7; B = 6;
	#1 A = 1; B = 1;
	#2 sel = 7; A = 0; B = 0;
	#1 A = 1; B = 1;
	#1 A = 15; B = 15;
	#1 A = 1; B = 15;
	#1 A = 10; B = 11;
	#1 A = 11; B = 10;
	#1 A = 8; B = 1;
	
  end 
	initial
    #145 $finish;
  initial begin
    $dumpfile("LAB8_tb.vcd");
    $dumpvars(0, LAB_8);
  end
endmodule

LAB/LAB 8/LAB8_tb.vcd
$date
	Thu Oct 22 18:34:57 2020
$end
$version
	Icarus Verilog
$end
$timescale
	1ps
$end
$scope module LAB_8 $end
$var wire 4 ! alu [3:0] $end
$var wire 8 " Memoria [7:0] $end
$var wire 12 # Contador [11:0] $end
$var reg 4 $ A [3:0] $end
$var reg 4 % B [3:0] $end
$var reg 1 & EC $end
$var reg 12 ' add [11:0] $end
$var reg 1 ( clk $end
$var reg 12 ) data [11:0] $end
$var reg 1 * load $end
$var reg 1 + reset $end
$var reg 3 , sel [2:0] $end
$scope module U1 $end
$var wire 1 ( clk $end
$var wire 12 - data [11:0] $end
$var wire 1 & enable $end
$var wire 1 * load $end
$var wire 1 + reset $end
$var reg 12 . out [11:0] $end
$upscope $end
$scope module U2 $end
$var wire 12 / address [11:0] $end
$var wire 8 0 data [7:0] $end
$upscope $end
$scope module U3 $end
$var wire 4 1 A [3:0] $end
$var wire 4 2 B [3:0] $end
$var wire 3 3 sel [2:0] $end
$var reg 5 4 X [4:0] $end
$var reg 4 5 Y [3:0] $end
$var reg 1 6 menor $end
$upscope $end
$upscope $end
$enddefinitions $end
#0
$dumpvars
x6
bx 5
bx 4
bx 3
bx 2
bx 1
bx 0
bx /
bx .
bx -
bx ,
x+
x*
bx )
0(
bx '
x&
bx %
bx $
bx #
bx "
bx !
$end
#1
1(
#2
0(
#3
b0 #
b0 .
1(
0&
0*
b10100 )
b10100 -
1+
#4
0(
0+
#5
1(
#6
0(
#7
1(
#8
0(
#9
b1 #
b1 .
1(
1&
#10
0(
#11
b10 #
b10 .
1(
#12
0(
#13
b11 #
b11 .
1(
#14
0(
#15
b100 #
b100 .
1(
#16
0(
#17
b101 #
b101 .
1(
#18
0(
#19
b110 #
b110 .
1(
#20
0(
#21
b111 #
b111 .
1(
#22
0(
#23
b1000 #
b1000 .
1(
#24
0(
#25
b1001 #
b1001 .
1(
#26
0(
#27
b1010 #
b1010 .
1(
#28
0(
#29
b10100 #
b10100 .
1(
1*
#30
0(
#31
1(
#32
0(
#33
1(
#34
0(
b110010 )
b110010 -
0*
#35
b10101 #
b10101 .
1(
#36
0(
#37
b10110 #
b10110 .
1(
#38
0(
#39
b110010 #
b110010 .
1(
1*
#40
0(
#41
1(
#42
0(
#43
1(
#44
0(
0*
#45
b110011 #
b110011 .
1(
#46
0(
#47
b110100 #
b110100 .
1(
#48
0(
#49
b110101 #
b110101 .
1(
#50
0(
#51
b110110 #
b110110 .
1(
#52
0(
#53
b110111 #
b110111 .
1(
#54
0(
0&
#55
1(
#56
0(
#57
1(
#58
0(
#59
1(
#60
0(
#61
b0 "
b0 0
1(
b0 '
b0 /
#62
0(
#63
b1 "
b1 0
1(
b110111 '
b110111 /
#64
0(
#65
b10 "
b10 0
1(
b1010000 '
b1010000 /
#66
0(
#67
b11 "
b11 0
1(
b1010101 '
b1010101 /
#68
0(
#69
b100 "
b100 0
1(
b1011111 '
b1011111 /
#70
0(
#71
b1100000 "
b1100000 0
1(
b1100000 '
b1100000 /
#72
0(
#73
b101 "
b101 0
1(
b1101 '
b1101 /
#74
0(
#75
b110 "
b110 0
1(
b100011 '
b100011 /
#76
0(
#77
b1100010 "
b1100010 0
1(
b1100010 '
b1100010 /
#78
0(
#79
b1000100 "
b1000100 0
1(
b1000100 '
b1000100 /
#80
b0 !
b0 5
0(
b0 %
b0 2
b0 $
b0 1
b0 ,
b0 3
#81
1(
b1 %
b1 2
#82
b1 !
b1 5
0(
b1 $
b1 1
#83
1(
b1111 %
b1111 2
#84
b1111 !
b1111 5
0(
b1111 $
b1111 1
#85
1(
#86
b0 !
b0 5
0(
b0 %
b0 2
b0 $
b0 1
b1 ,
b1 3
#87
b1111 !
b1111 5
1(
b1111 $
b1111 1
#88
b0 !
b0 5
0(
b0 $
b0 1
#89
b1111 !
b1111 5
1(
b1111 %
b1111 2
#90
0(
b1111 $
b1111 1
#91
1(
#92
b0 !
b0 5
b0 4
0(
b0 %
b0 2
b0 $
b0 1
b10 ,
b10 3
#93
b10 !
b10 5
b10 4
1(
b1 %
b1 2
b1 $
b1 1
#94
b1111 !
b1111 5
b1111 4
0(
b0 %
b0 2
b1111 $
b1111 1
#95
b1010 !
b1010 5
b1010 4
1(
b11 %
b11 2
b111 $
b111 1
#96
b0 !
b0 5
b10000 4
0(
b1 %
b1 2
b1111 $
b1111 1
#97
1(
#98
0(
b11 ,
b11 3
#99
1(
b1 $
b1 1
#100
0(
b1111 %
b1111 2
b1111 $
b1111 1
#101
1(
#102
0(
b0 %
b0 2
b0 $
b0 1
b100 ,
b100 3
#103
b1111 !
b1111 5
1(
b1111 $
b1111 1
#104
b0 !
b0 5
0(
b1111 %
b1111 2
#105
1(
#106
b1111 !
b1111 5
0(
b0 %
b0 2
b0 $
b0 1
b101 ,
b101 3
#107
b0 !
b0 5
1(
b1111 %
b1111 2
#108
b1111 !
b1111 5
0(
b1111 $
b1111 1
#109
1(
b0 %
b0 2
#110
0(
#111
b0 !
b0 5
b0 4
1(
b0 $
b0 1
b110 ,
b110 3
#112
b1001 !
b1001 5
b1001 4
0(
b1 %
b1 2
b1010 $
b1010 1
#113
b101 !
b101 5
b101 4
1(
b1010 %
b1010 2
b1111 $
b1111 1
#114
b1 !
b1 5
b1 4
0(
b110 %
b110 2
b111 $
b111 1
#115
b0 !
b0 5
b0 4
1(
b1 %
b1 2
b1 $
b1 1
#116
0(
#117
06
1(
b0 %
b0 2
b0 $
b0 1
b111 ,
b111 3
#118
0(
b1 %
b1 2
b1 $
b1 1
#119
1(
b1111 %
b1111 2
b1111 $
b1111 1
#120
b1111 !
b1111 5
16
0(
b1 $
b1 1
#121
1(
b1011 %
b1011 2
b1010 $
b1010 1
#122
b0 !
b0 5
06
0(
b1010 %
b1010 2
b1011 $
b1011 1
#123
1(
b1 %
b1 2
b1000 $
b1000 1
