LAB/LAB 9/Ejercicio 2/ejercicio2.v
//Ejercicio 2

module FlipD1(input wire CLK, input wire D, input wire reset, input wire enable, output Q);
reg Q;
	always @(posedge CLK or	posedge reset)
		if (reset)begin
		Q <= 0;
	end else if(enable) begin
		Q <= D;
	end
endmodule

//modulo FlipFlop T
module FlipT(input wire CLK, reset, enable, output wire Q);
	FlipD1 O5(CLK, ~Q, reset, enable, Q);
endmodule

LAB/LAB 9/Ejercicio 2/ejercicio2_tb.v
module Ejercicio_2();

  reg Clk, reset, enable; 
  wire QT; 

//Variables para módulo
	FlipT U4(Clk, reset, enable, QT);


initial begin
	Clk=0;
	forever #1 Clk = ~Clk;
end


//Prueba para FLipT
  initial begin
	#3
    $display("\n");
	$display("Ejercicio 2");
    $display("Clk E R |  Q");
    $display("-----------------");
    $monitor("%b   %b %b | %b", Clk, enable, reset, QT);
	//es escogieron números aleatorios para A
       reset = 1; enable = 0;
    #1 reset = 0; enable = 1;

  end

	initial
    #15 $finish;
  initial begin
    $dumpfile("ejercicio2_tb.vcd");
    $dumpvars(0, Ejercicio_2);
  end
endmodule

LAB/LAB 9/Ejercicio 2/ejercicio2_tb.vcd
$date
	Fri Oct 30 16:29:16 2020
$end
$version
	Icarus Verilog
$end
$timescale
	1ps
$end
$scope module Ejercicio_2 $end
$var wire 1 ! QT $end
$var reg 1 " Clk $end
$var reg 1 # enable $end
$var reg 1 $ reset $end
$scope module U4 $end
$var wire 1 " CLK $end
$var wire 1 # enable $end
$var wire 1 $ reset $end
$var wire 1 ! Q $end
$scope module O5 $end
$var wire 1 " CLK $end
$var wire 1 % D $end
$var wire 1 # enable $end
$var wire 1 $ reset $end
$var reg 1 ! Q $end
$upscope $end
$upscope $end
$upscope $end
$enddefinitions $end
#0
$dumpvars
x%
x$
x#
0"
x!
$end
#1
1"
#2
0"
#3
1%
0!
1"
0#
1$
#4
0"
1#
0$
#5
0%
1!
1"
#6
0"
#7
1%
0!
1"
#8
0"
#9
0%
1!
1"
#10
0"
#11
1%
0!
1"
#12
0"
#13
0%
1!
1"
#14
0"
#15
1%
0!
1"
